eoq3pyaccesscontroller/__init__.py
eoq3pyaccesscontroller/elementpermissioncacheentry.py
eoq3pyaccesscontroller/genericpermission.py
eoq3pyaccesscontroller/pyaccesscontroller.py
eoq3pyaccesscontroller/userrecord.py
eoq3pyaccesscontroller/model/__init__.py
eoq3pyaccesscontroller/model/accesssettings.py
eoq3pyaccesscontroller/model/modeltopy.py
eoq3pyaccesscontroller/util/__init__.py
eoq3pyaccesscontroller/util/generatepasshash.py
eoq3pyaccesscontroller/util/passhash.py
eoq3pyaccesscontroller-2.9.1.dist-info/LICENSE
eoq3pyaccesscontroller-2.9.1.dist-info/METADATA
eoq3pyaccesscontroller-2.9.1.dist-info/WHEEL
eoq3pyaccesscontroller-2.9.1.dist-info/top_level.txt
eoq3pyaccesscontroller-2.9.1.dist-info/RECORD
