Metadata-Version: 2.1
Name: eoq3pyaccesscontroller
Version: 2.9.1
Summary: Access control for an eoq3 DomainWithMdb
Author-email: Bjoern Annighoefer <bjoern.annighoefer@ils.uni-stuttgart.de>
Project-URL: Homepage, https://gitlab.com/eoq/py/eoq3pyaccesscontroller
Project-URL: Issues, https://gitlab.com/eoq/py/eoq3pyaccesscontroller/-/issues
Classifier: Programming Language :: Python :: 3
Classifier: License :: OSI Approved :: MIT License
Classifier: Operating System :: OS Independent
Requires-Python: >=3.10
License-File: LICENSE
Requires-Dist: eoq3
